{"pageProps":{"bookInfo":{"id":"0873cd716d085c9ca261d622747f295b","name":"高等数学","fullPath":"F:\\passerby\\math\\高等数学","chapterList":[{"id":"0873cd716d085c9ca261d622747f295b_9a774cae016b7bb1265300c4bd52f802","type":"chapter","name":"01.函数、极限与连续.md","fullPath":"F:\\passerby\\math\\高等数学\\01.函数、极限与连续.md","url":"/chapter/0873cd716d085c9ca261d622747f295b_9a774cae016b7bb1265300c4bd52f802"},{"id":"0873cd716d085c9ca261d622747f295b_b1879c5b86c700a66f46c899285b7ea1","type":"chapter","name":"02.导数、微分及其应用.md","fullPath":"F:\\passerby\\math\\高等数学\\02.导数、微分及其应用.md","url":"/chapter/0873cd716d085c9ca261d622747f295b_b1879c5b86c700a66f46c899285b7ea1"}],"title":"02.导数、微分及其应用","type":"book","url":"/book/0873cd716d085c9ca261d622747f295b","content":"\n    \n    \n      <div class=\"crossnote markdown-preview  \">\n      \n<h1 id=\"导数-微分及其应用\">导数、微分及其应用 </h1>\n<h2 id=\"导数与微分\">导数与微分 </h2>\n<h3 id=\"导数的概念\">导数的概念 </h3>\n<p>设直线<span class=\"katex\"><span class=\"katex-mathml\"><math xmlns=\"http://www.w3.org/1998/Math/MathML\"><semantics><mrow><mi>y</mi><mo>=</mo><mi>k</mi><mi>x</mi><mo>+</mo><mi>b</mi></mrow><annotation encoding=\"application/x-tex\">y = kx + b</annotation></semantics></math></span><span class=\"katex-html\" aria-hidden=\"true\"><span class=\"base\"><span class=\"strut\" style=\"height:0.625em;vertical-align:-0.1944em;\"></span><span class=\"mord mathnormal\" style=\"margin-right:0.03588em;\">y</span><span class=\"mspace\" style=\"margin-right:0.2778em;\"></span><span class=\"mrel\">=</span><span class=\"mspace\" style=\"margin-right:0.2778em;\"></span></span><span class=\"base\"><span class=\"strut\" style=\"height:0.7778em;vertical-align:-0.0833em;\"></span><span class=\"mord mathnormal\" style=\"margin-right:0.03148em;\">k</span><span class=\"mord mathnormal\">x</span><span class=\"mspace\" style=\"margin-right:0.2222em;\"></span><span class=\"mbin\">+</span><span class=\"mspace\" style=\"margin-right:0.2222em;\"></span></span><span class=\"base\"><span class=\"strut\" style=\"height:0.6944em;\"></span><span class=\"mord mathnormal\">b</span></span></span></span>倾斜角为<span class=\"katex\"><span class=\"katex-mathml\"><math xmlns=\"http://www.w3.org/1998/Math/MathML\"><semantics><mrow><mi>α</mi></mrow><annotation encoding=\"application/x-tex\">\\alpha</annotation></semantics></math></span><span class=\"katex-html\" aria-hidden=\"true\"><span class=\"base\"><span class=\"strut\" style=\"height:0.4306em;\"></span><span class=\"mord mathnormal\" style=\"margin-right:0.0037em;\">α</span></span></span></span>.点<span class=\"katex\"><span class=\"katex-mathml\"><math xmlns=\"http://www.w3.org/1998/Math/MathML\"><semantics><mrow><msub><mi>P</mi><mn>1</mn></msub><mo stretchy=\"false\">(</mo><msub><mi>x</mi><mn>1</mn></msub><mo separator=\"true\">,</mo><msub><mi>y</mi><mn>1</mn></msub><mo stretchy=\"false\">)</mo><mtext>和点</mtext><msub><mi>P</mi><mn>2</mn></msub><mo stretchy=\"false\">(</mo><msub><mi>x</mi><mn>2</mn></msub><mo separator=\"true\">,</mo><msub><mi>y</mi><mn>2</mn></msub><mo stretchy=\"false\">)</mo></mrow><annotation encoding=\"application/x-tex\">P_1(x_1, y_1)和点P_2(x_2,y_2)</annotation></semantics></math></span><span class=\"katex-html\" aria-hidden=\"true\"><span class=\"base\"><span class=\"strut\" style=\"height:1em;vertical-align:-0.25em;\"></span><span class=\"mord\"><span class=\"mord mathnormal\" style=\"margin-right:0.13889em;\">P</span><span class=\"msupsub\"><span class=\"vlist-t vlist-t2\"><span class=\"vlist-r\"><span class=\"vlist\" style=\"height:0.3011em;\"><span style=\"top:-2.55em;margin-left:-0.1389em;margin-right:0.05em;\"><span class=\"pstrut\" style=\"height:2.7em;\"></span><span class=\"sizing reset-size6 size3 mtight\"><span class=\"mord mtight\">1</span></span></span></span><span class=\"vlist-s\">​</span></span><span class=\"vlist-r\"><span class=\"vlist\" style=\"height:0.15em;\"><span></span></span></span></span></span></span><span class=\"mopen\">(</span><span class=\"mord\"><span class=\"mord mathnormal\">x</span><span class=\"msupsub\"><span class=\"vlist-t vlist-t2\"><span class=\"vlist-r\"><span class=\"vlist\" style=\"height:0.3011em;\"><span style=\"top:-2.55em;margin-left:0em;margin-right:0.05em;\"><span class=\"pstrut\" style=\"height:2.7em;\"></span><span class=\"sizing reset-size6 size3 mtight\"><span class=\"mord mtight\">1</span></span></span></span><span class=\"vlist-s\">​</span></span><span class=\"vlist-r\"><span class=\"vlist\" style=\"height:0.15em;\"><span></span></span></span></span></span></span><span class=\"mpunct\">,</span><span class=\"mspace\" style=\"margin-right:0.1667em;\"></span><span class=\"mord\"><span class=\"mord mathnormal\" style=\"margin-right:0.03588em;\">y</span><span class=\"msupsub\"><span class=\"vlist-t vlist-t2\"><span class=\"vlist-r\"><span class=\"vlist\" style=\"height:0.3011em;\"><span style=\"top:-2.55em;margin-left:-0.0359em;margin-right:0.05em;\"><span class=\"pstrut\" style=\"height:2.7em;\"></span><span class=\"sizing reset-size6 size3 mtight\"><span class=\"mord mtight\">1</span></span></span></span><span class=\"vlist-s\">​</span></span><span class=\"vlist-r\"><span class=\"vlist\" style=\"height:0.15em;\"><span></span></span></span></span></span></span><span class=\"mclose\">)</span><span class=\"mord cjk_fallback\">和点</span><span class=\"mord\"><span class=\"mord mathnormal\" style=\"margin-right:0.13889em;\">P</span><span class=\"msupsub\"><span class=\"vlist-t vlist-t2\"><span class=\"vlist-r\"><span class=\"vlist\" style=\"height:0.3011em;\"><span style=\"top:-2.55em;margin-left:-0.1389em;margin-right:0.05em;\"><span class=\"pstrut\" style=\"height:2.7em;\"></span><span class=\"sizing reset-size6 size3 mtight\"><span class=\"mord mtight\">2</span></span></span></span><span class=\"vlist-s\">​</span></span><span class=\"vlist-r\"><span class=\"vlist\" style=\"height:0.15em;\"><span></span></span></span></span></span></span><span class=\"mopen\">(</span><span class=\"mord\"><span class=\"mord mathnormal\">x</span><span class=\"msupsub\"><span class=\"vlist-t vlist-t2\"><span class=\"vlist-r\"><span class=\"vlist\" style=\"height:0.3011em;\"><span style=\"top:-2.55em;margin-left:0em;margin-right:0.05em;\"><span class=\"pstrut\" style=\"height:2.7em;\"></span><span class=\"sizing reset-size6 size3 mtight\"><span class=\"mord mtight\">2</span></span></span></span><span class=\"vlist-s\">​</span></span><span class=\"vlist-r\"><span class=\"vlist\" style=\"height:0.15em;\"><span></span></span></span></span></span></span><span class=\"mpunct\">,</span><span class=\"mspace\" style=\"margin-right:0.1667em;\"></span><span class=\"mord\"><span class=\"mord mathnormal\" style=\"margin-right:0.03588em;\">y</span><span class=\"msupsub\"><span class=\"vlist-t vlist-t2\"><span class=\"vlist-r\"><span class=\"vlist\" style=\"height:0.3011em;\"><span style=\"top:-2.55em;margin-left:-0.0359em;margin-right:0.05em;\"><span class=\"pstrut\" style=\"height:2.7em;\"></span><span class=\"sizing reset-size6 size3 mtight\"><span class=\"mord mtight\">2</span></span></span></span><span class=\"vlist-s\">​</span></span><span class=\"vlist-r\"><span class=\"vlist\" style=\"height:0.15em;\"><span></span></span></span></span></span></span><span class=\"mclose\">)</span></span></span></span>为直线上的任意两点，则当<span class=\"katex\"><span class=\"katex-mathml\"><math xmlns=\"http://www.w3.org/1998/Math/MathML\"><semantics><mrow><msub><mi>x</mi><mn>1</mn></msub><mo mathvariant=\"normal\">≠</mo><msub><mi>x</mi><mn>2</mn></msub></mrow><annotation encoding=\"application/x-tex\">x_1 \\neq x_2</annotation></semantics></math></span><span class=\"katex-html\" aria-hidden=\"true\"><span class=\"base\"><span class=\"strut\" style=\"height:0.8889em;vertical-align:-0.1944em;\"></span><span class=\"mord\"><span class=\"mord mathnormal\">x</span><span class=\"msupsub\"><span class=\"vlist-t vlist-t2\"><span class=\"vlist-r\"><span class=\"vlist\" style=\"height:0.3011em;\"><span style=\"top:-2.55em;margin-left:0em;margin-right:0.05em;\"><span class=\"pstrut\" style=\"height:2.7em;\"></span><span class=\"sizing reset-size6 size3 mtight\"><span class=\"mord mtight\">1</span></span></span></span><span class=\"vlist-s\">​</span></span><span class=\"vlist-r\"><span class=\"vlist\" style=\"height:0.15em;\"><span></span></span></span></span></span></span><span class=\"mspace\" style=\"margin-right:0.2778em;\"></span><span class=\"mrel\"><span class=\"mrel\"><span class=\"mord vbox\"><span class=\"thinbox\"><span class=\"rlap\"><span class=\"strut\" style=\"height:0.8889em;vertical-align:-0.1944em;\"></span><span class=\"inner\"><span class=\"mord\"><span class=\"mrel\"></span></span></span><span class=\"fix\"></span></span></span></span></span><span class=\"mrel\">=</span></span><span class=\"mspace\" style=\"margin-right:0.2778em;\"></span></span><span class=\"base\"><span class=\"strut\" style=\"height:0.5806em;vertical-align:-0.15em;\"></span><span class=\"mord\"><span class=\"mord mathnormal\">x</span><span class=\"msupsub\"><span class=\"vlist-t vlist-t2\"><span class=\"vlist-r\"><span class=\"vlist\" style=\"height:0.3011em;\"><span style=\"top:-2.55em;margin-left:0em;margin-right:0.05em;\"><span class=\"pstrut\" style=\"height:2.7em;\"></span><span class=\"sizing reset-size6 size3 mtight\"><span class=\"mord mtight\">2</span></span></span></span><span class=\"vlist-s\">​</span></span><span class=\"vlist-r\"><span class=\"vlist\" style=\"height:0.15em;\"><span></span></span></span></span></span></span></span></span></span>,直线的斜率为<span class=\"katex-display\"><span class=\"katex\"><span class=\"katex-mathml\"><math xmlns=\"http://www.w3.org/1998/Math/MathML\" display=\"block\"><semantics><mrow><mi>k</mi><mo>=</mo><mi>tan</mi><mo>⁡</mo><mi>α</mi><mo>=</mo><mfrac><mrow><msub><mi>y</mi><mn>2</mn></msub><mo>−</mo><msub><mi>y</mi><mn>1</mn></msub></mrow><mrow><msub><mi>x</mi><mn>2</mn></msub><mo>−</mo><msub><mi>x</mi><mn>1</mn></msub></mrow></mfrac></mrow><annotation encoding=\"application/x-tex\">k = \\tan \\alpha = \\frac{y_2 - y_1}{x_2 - x_1}</annotation></semantics></math></span><span class=\"katex-html\" aria-hidden=\"true\"><span class=\"base\"><span class=\"strut\" style=\"height:0.6944em;\"></span><span class=\"mord mathnormal\" style=\"margin-right:0.03148em;\">k</span><span class=\"mspace\" style=\"margin-right:0.2778em;\"></span><span class=\"mrel\">=</span><span class=\"mspace\" style=\"margin-right:0.2778em;\"></span></span><span class=\"base\"><span class=\"strut\" style=\"height:0.6151em;\"></span><span class=\"mop\">tan</span><span class=\"mspace\" style=\"margin-right:0.1667em;\"></span><span class=\"mord mathnormal\" style=\"margin-right:0.0037em;\">α</span><span class=\"mspace\" style=\"margin-right:0.2778em;\"></span><span class=\"mrel\">=</span><span class=\"mspace\" style=\"margin-right:0.2778em;\"></span></span><span class=\"base\"><span class=\"strut\" style=\"height:2.0963em;vertical-align:-0.836em;\"></span><span class=\"mord\"><span class=\"mopen nulldelimiter\"></span><span class=\"mfrac\"><span class=\"vlist-t vlist-t2\"><span class=\"vlist-r\"><span class=\"vlist\" style=\"height:1.2603em;\"><span style=\"top:-2.314em;\"><span class=\"pstrut\" style=\"height:3em;\"></span><span class=\"mord\"><span class=\"mord\"><span class=\"mord mathnormal\">x</span><span class=\"msupsub\"><span class=\"vlist-t vlist-t2\"><span class=\"vlist-r\"><span class=\"vlist\" style=\"height:0.3011em;\"><span style=\"top:-2.55em;margin-left:0em;margin-right:0.05em;\"><span class=\"pstrut\" style=\"height:2.7em;\"></span><span class=\"sizing reset-size6 size3 mtight\"><span class=\"mord mtight\">2</span></span></span></span><span class=\"vlist-s\">​</span></span><span class=\"vlist-r\"><span class=\"vlist\" style=\"height:0.15em;\"><span></span></span></span></span></span></span><span class=\"mspace\" style=\"margin-right:0.2222em;\"></span><span class=\"mbin\">−</span><span class=\"mspace\" style=\"margin-right:0.2222em;\"></span><span class=\"mord\"><span class=\"mord mathnormal\">x</span><span class=\"msupsub\"><span class=\"vlist-t vlist-t2\"><span class=\"vlist-r\"><span class=\"vlist\" style=\"height:0.3011em;\"><span style=\"top:-2.55em;margin-left:0em;margin-right:0.05em;\"><span class=\"pstrut\" style=\"height:2.7em;\"></span><span class=\"sizing reset-size6 size3 mtight\"><span class=\"mord mtight\">1</span></span></span></span><span class=\"vlist-s\">​</span></span><span class=\"vlist-r\"><span class=\"vlist\" style=\"height:0.15em;\"><span></span></span></span></span></span></span></span></span><span style=\"top:-3.23em;\"><span class=\"pstrut\" style=\"height:3em;\"></span><span class=\"frac-line\" style=\"border-bottom-width:0.04em;\"></span></span><span style=\"top:-3.677em;\"><span class=\"pstrut\" style=\"height:3em;\"></span><span class=\"mord\"><span class=\"mord\"><span class=\"mord mathnormal\" style=\"margin-right:0.03588em;\">y</span><span class=\"msupsub\"><span class=\"vlist-t vlist-t2\"><span class=\"vlist-r\"><span class=\"vlist\" style=\"height:0.3011em;\"><span style=\"top:-2.55em;margin-left:-0.0359em;margin-right:0.05em;\"><span class=\"pstrut\" style=\"height:2.7em;\"></span><span class=\"sizing reset-size6 size3 mtight\"><span class=\"mord mtight\">2</span></span></span></span><span class=\"vlist-s\">​</span></span><span class=\"vlist-r\"><span class=\"vlist\" style=\"height:0.15em;\"><span></span></span></span></span></span></span><span class=\"mspace\" style=\"margin-right:0.2222em;\"></span><span class=\"mbin\">−</span><span class=\"mspace\" style=\"margin-right:0.2222em;\"></span><span class=\"mord\"><span class=\"mord mathnormal\" style=\"margin-right:0.03588em;\">y</span><span class=\"msupsub\"><span class=\"vlist-t vlist-t2\"><span class=\"vlist-r\"><span class=\"vlist\" style=\"height:0.3011em;\"><span style=\"top:-2.55em;margin-left:-0.0359em;margin-right:0.05em;\"><span class=\"pstrut\" style=\"height:2.7em;\"></span><span class=\"sizing reset-size6 size3 mtight\"><span class=\"mord mtight\">1</span></span></span></span><span class=\"vlist-s\">​</span></span><span class=\"vlist-r\"><span class=\"vlist\" style=\"height:0.15em;\"><span></span></span></span></span></span></span></span></span></span><span class=\"vlist-s\">​</span></span><span class=\"vlist-r\"><span class=\"vlist\" style=\"height:0.836em;\"><span></span></span></span></span></span><span class=\"mclose nulldelimiter\"></span></span></span></span></span></span></p>\n<p>如下图所示，研究经过曲线上一点P的切线，选择曲线上的任意点Q,作割线PQ;然后让点Q沿着曲线趋近于点P，判断此时割线斜率的极限是否存在，如果存在，就把以这个极限值为斜率的直线定义为<strong>曲线在点P的切线</strong><br>\n<img src=\"/assets/17362527181499189.png\" alt=\"切线\"></p>\n<h3 id=\"例-求函数yx2在点p11处的切线\">例 求函数<span class=\"katex\"><span class=\"katex-mathml\"><math xmlns=\"http://www.w3.org/1998/Math/MathML\"><semantics><mrow><mi>y</mi><mo>=</mo><msup><mi>x</mi><mn>2</mn></msup></mrow><annotation encoding=\"application/x-tex\">y=x^2</annotation></semantics></math></span><span class=\"katex-html\" aria-hidden=\"true\"><span class=\"base\"><span class=\"strut\" style=\"height:0.625em;vertical-align:-0.1944em;\"></span><span class=\"mord mathnormal\" style=\"margin-right:0.03588em;\">y</span><span class=\"mspace\" style=\"margin-right:0.2778em;\"></span><span class=\"mrel\">=</span><span class=\"mspace\" style=\"margin-right:0.2778em;\"></span></span><span class=\"base\"><span class=\"strut\" style=\"height:0.8141em;\"></span><span class=\"mord\"><span class=\"mord mathnormal\">x</span><span class=\"msupsub\"><span class=\"vlist-t\"><span class=\"vlist-r\"><span class=\"vlist\" style=\"height:0.8141em;\"><span style=\"top:-3.063em;margin-right:0.05em;\"><span class=\"pstrut\" style=\"height:2.7em;\"></span><span class=\"sizing reset-size6 size3 mtight\"><span class=\"mord mtight\">2</span></span></span></span></span></span></span></span></span></span></span>在点P(1,1)处的切线 </h3>\n<p>设<span class=\"katex\"><span class=\"katex-mathml\"><math xmlns=\"http://www.w3.org/1998/Math/MathML\"><semantics><mrow><mi>Q</mi><mo stretchy=\"false\">(</mo><mi>x</mi><mo separator=\"true\">,</mo><msup><mi>x</mi><mn>2</mn></msup><mo stretchy=\"false\">)</mo></mrow><annotation encoding=\"application/x-tex\">Q(x,x^2)</annotation></semantics></math></span><span class=\"katex-html\" aria-hidden=\"true\"><span class=\"base\"><span class=\"strut\" style=\"height:1.0641em;vertical-align:-0.25em;\"></span><span class=\"mord mathnormal\">Q</span><span class=\"mopen\">(</span><span class=\"mord mathnormal\">x</span><span class=\"mpunct\">,</span><span class=\"mspace\" style=\"margin-right:0.1667em;\"></span><span class=\"mord\"><span class=\"mord mathnormal\">x</span><span class=\"msupsub\"><span class=\"vlist-t\"><span class=\"vlist-r\"><span class=\"vlist\" style=\"height:0.8141em;\"><span style=\"top:-3.063em;margin-right:0.05em;\"><span class=\"pstrut\" style=\"height:2.7em;\"></span><span class=\"sizing reset-size6 size3 mtight\"><span class=\"mord mtight\">2</span></span></span></span></span></span></span></span><span class=\"mclose\">)</span></span></span></span>为抛物线<span class=\"katex\"><span class=\"katex-mathml\"><math xmlns=\"http://www.w3.org/1998/Math/MathML\"><semantics><mrow><mi>y</mi><mo>=</mo><msup><mi>x</mi><mn>2</mn></msup></mrow><annotation encoding=\"application/x-tex\">y = x^2</annotation></semantics></math></span><span class=\"katex-html\" aria-hidden=\"true\"><span class=\"base\"><span class=\"strut\" style=\"height:0.625em;vertical-align:-0.1944em;\"></span><span class=\"mord mathnormal\" style=\"margin-right:0.03588em;\">y</span><span class=\"mspace\" style=\"margin-right:0.2778em;\"></span><span class=\"mrel\">=</span><span class=\"mspace\" style=\"margin-right:0.2778em;\"></span></span><span class=\"base\"><span class=\"strut\" style=\"height:0.8141em;\"></span><span class=\"mord\"><span class=\"mord mathnormal\">x</span><span class=\"msupsub\"><span class=\"vlist-t\"><span class=\"vlist-r\"><span class=\"vlist\" style=\"height:0.8141em;\"><span style=\"top:-3.063em;margin-right:0.05em;\"><span class=\"pstrut\" style=\"height:2.7em;\"></span><span class=\"sizing reset-size6 size3 mtight\"><span class=\"mord mtight\">2</span></span></span></span></span></span></span></span></span></span></span>上的任意一点，在点P(1,1)处<span class=\"katex\"><span class=\"katex-mathml\"><math xmlns=\"http://www.w3.org/1998/Math/MathML\"><semantics><mrow><mi mathvariant=\"normal\">Δ</mi><mi>x</mi><mo>=</mo><mi>x</mi><mo>−</mo><mn>1</mn></mrow><annotation encoding=\"application/x-tex\">\\Delta x = x - 1</annotation></semantics></math></span><span class=\"katex-html\" aria-hidden=\"true\"><span class=\"base\"><span class=\"strut\" style=\"height:0.6833em;\"></span><span class=\"mord\">Δ</span><span class=\"mord mathnormal\">x</span><span class=\"mspace\" style=\"margin-right:0.2778em;\"></span><span class=\"mrel\">=</span><span class=\"mspace\" style=\"margin-right:0.2778em;\"></span></span><span class=\"base\"><span class=\"strut\" style=\"height:0.6667em;vertical-align:-0.0833em;\"></span><span class=\"mord mathnormal\">x</span><span class=\"mspace\" style=\"margin-right:0.2222em;\"></span><span class=\"mbin\">−</span><span class=\"mspace\" style=\"margin-right:0.2222em;\"></span></span><span class=\"base\"><span class=\"strut\" style=\"height:0.6444em;\"></span><span class=\"mord\">1</span></span></span></span>为自变量的改变量，<span class=\"katex\"><span class=\"katex-mathml\"><math xmlns=\"http://www.w3.org/1998/Math/MathML\"><semantics><mrow><mi mathvariant=\"normal\">Δ</mi><mi>y</mi><mo>=</mo><msup><mi>x</mi><mn>2</mn></msup><mo>−</mo><mn>1</mn></mrow><annotation encoding=\"application/x-tex\">\\Delta y = x^2 - 1</annotation></semantics></math></span><span class=\"katex-html\" aria-hidden=\"true\"><span class=\"base\"><span class=\"strut\" style=\"height:0.8778em;vertical-align:-0.1944em;\"></span><span class=\"mord\">Δ</span><span class=\"mord mathnormal\" style=\"margin-right:0.03588em;\">y</span><span class=\"mspace\" style=\"margin-right:0.2778em;\"></span><span class=\"mrel\">=</span><span class=\"mspace\" style=\"margin-right:0.2778em;\"></span></span><span class=\"base\"><span class=\"strut\" style=\"height:0.8974em;vertical-align:-0.0833em;\"></span><span class=\"mord\"><span class=\"mord mathnormal\">x</span><span class=\"msupsub\"><span class=\"vlist-t\"><span class=\"vlist-r\"><span class=\"vlist\" style=\"height:0.8141em;\"><span style=\"top:-3.063em;margin-right:0.05em;\"><span class=\"pstrut\" style=\"height:2.7em;\"></span><span class=\"sizing reset-size6 size3 mtight\"><span class=\"mord mtight\">2</span></span></span></span></span></span></span></span><span class=\"mspace\" style=\"margin-right:0.2222em;\"></span><span class=\"mbin\">−</span><span class=\"mspace\" style=\"margin-right:0.2222em;\"></span></span><span class=\"base\"><span class=\"strut\" style=\"height:0.6444em;\"></span><span class=\"mord\">1</span></span></span></span>为函数的因变量，则割线的斜率为<br>\n<span class=\"katex-display\"><span class=\"katex\"><span class=\"katex-mathml\"><math xmlns=\"http://www.w3.org/1998/Math/MathML\" display=\"block\"><semantics><mrow><mfrac><mrow><mi mathvariant=\"normal\">Δ</mi><mi>y</mi></mrow><mrow><mi mathvariant=\"normal\">Δ</mi><mi>x</mi></mrow></mfrac><mo>=</mo><mfrac><mrow><msup><mi>x</mi><mn>2</mn></msup><mo>−</mo><mn>1</mn></mrow><mrow><mi>x</mi><mo>−</mo><mn>1</mn></mrow></mfrac></mrow><annotation encoding=\"application/x-tex\">\\frac{\\Delta y}{\\Delta x} = \\frac{x^2 -1}{x - 1}</annotation></semantics></math></span><span class=\"katex-html\" aria-hidden=\"true\"><span class=\"base\"><span class=\"strut\" style=\"height:2.0463em;vertical-align:-0.686em;\"></span><span class=\"mord\"><span class=\"mopen nulldelimiter\"></span><span class=\"mfrac\"><span class=\"vlist-t vlist-t2\"><span class=\"vlist-r\"><span class=\"vlist\" style=\"height:1.3603em;\"><span style=\"top:-2.314em;\"><span class=\"pstrut\" style=\"height:3em;\"></span><span class=\"mord\"><span class=\"mord\">Δ</span><span class=\"mord mathnormal\">x</span></span></span><span style=\"top:-3.23em;\"><span class=\"pstrut\" style=\"height:3em;\"></span><span class=\"frac-line\" style=\"border-bottom-width:0.04em;\"></span></span><span style=\"top:-3.677em;\"><span class=\"pstrut\" style=\"height:3em;\"></span><span class=\"mord\"><span class=\"mord\">Δ</span><span class=\"mord mathnormal\" style=\"margin-right:0.03588em;\">y</span></span></span></span><span class=\"vlist-s\">​</span></span><span class=\"vlist-r\"><span class=\"vlist\" style=\"height:0.686em;\"><span></span></span></span></span></span><span class=\"mclose nulldelimiter\"></span></span><span class=\"mspace\" style=\"margin-right:0.2778em;\"></span><span class=\"mrel\">=</span><span class=\"mspace\" style=\"margin-right:0.2778em;\"></span></span><span class=\"base\"><span class=\"strut\" style=\"height:2.2604em;vertical-align:-0.7693em;\"></span><span class=\"mord\"><span class=\"mopen nulldelimiter\"></span><span class=\"mfrac\"><span class=\"vlist-t vlist-t2\"><span class=\"vlist-r\"><span class=\"vlist\" style=\"height:1.4911em;\"><span style=\"top:-2.314em;\"><span class=\"pstrut\" style=\"height:3em;\"></span><span class=\"mord\"><span class=\"mord mathnormal\">x</span><span class=\"mspace\" style=\"margin-right:0.2222em;\"></span><span class=\"mbin\">−</span><span class=\"mspace\" style=\"margin-right:0.2222em;\"></span><span class=\"mord\">1</span></span></span><span style=\"top:-3.23em;\"><span class=\"pstrut\" style=\"height:3em;\"></span><span class=\"frac-line\" style=\"border-bottom-width:0.04em;\"></span></span><span style=\"top:-3.677em;\"><span class=\"pstrut\" style=\"height:3em;\"></span><span class=\"mord\"><span class=\"mord\"><span class=\"mord mathnormal\">x</span><span class=\"msupsub\"><span class=\"vlist-t\"><span class=\"vlist-r\"><span class=\"vlist\" style=\"height:0.8141em;\"><span style=\"top:-3.063em;margin-right:0.05em;\"><span class=\"pstrut\" style=\"height:2.7em;\"></span><span class=\"sizing reset-size6 size3 mtight\"><span class=\"mord mtight\">2</span></span></span></span></span></span></span></span><span class=\"mspace\" style=\"margin-right:0.2222em;\"></span><span class=\"mbin\">−</span><span class=\"mspace\" style=\"margin-right:0.2222em;\"></span><span class=\"mord\">1</span></span></span></span><span class=\"vlist-s\">​</span></span><span class=\"vlist-r\"><span class=\"vlist\" style=\"height:0.7693em;\"><span></span></span></span></span></span><span class=\"mclose nulldelimiter\"></span></span></span></span></span></span></p>\n<p>当点Q沿着抛物线趋近于点P时，<span class=\"katex\"><span class=\"katex-mathml\"><math xmlns=\"http://www.w3.org/1998/Math/MathML\"><semantics><mrow><mi mathvariant=\"normal\">Δ</mi><mi>x</mi><mo>→</mo><mn>0</mn></mrow><annotation encoding=\"application/x-tex\">\\Delta x \\rightarrow 0</annotation></semantics></math></span><span class=\"katex-html\" aria-hidden=\"true\"><span class=\"base\"><span class=\"strut\" style=\"height:0.6833em;\"></span><span class=\"mord\">Δ</span><span class=\"mord mathnormal\">x</span><span class=\"mspace\" style=\"margin-right:0.2778em;\"></span><span class=\"mrel\">→</span><span class=\"mspace\" style=\"margin-right:0.2778em;\"></span></span><span class=\"base\"><span class=\"strut\" style=\"height:0.6444em;\"></span><span class=\"mord\">0</span></span></span></span>,此时<span class=\"katex\"><span class=\"katex-mathml\"><math xmlns=\"http://www.w3.org/1998/Math/MathML\"><semantics><mrow><mi>x</mi><mo>→</mo><mn>1</mn></mrow><annotation encoding=\"application/x-tex\">x \\rightarrow 1</annotation></semantics></math></span><span class=\"katex-html\" aria-hidden=\"true\"><span class=\"base\"><span class=\"strut\" style=\"height:0.4306em;\"></span><span class=\"mord mathnormal\">x</span><span class=\"mspace\" style=\"margin-right:0.2778em;\"></span><span class=\"mrel\">→</span><span class=\"mspace\" style=\"margin-right:0.2778em;\"></span></span><span class=\"base\"><span class=\"strut\" style=\"height:0.6444em;\"></span><span class=\"mord\">1</span></span></span></span>,割线QP的极限位置为PT</p>\n<p><span class=\"katex-display\"><span class=\"katex\"><span class=\"katex-mathml\"><math xmlns=\"http://www.w3.org/1998/Math/MathML\" display=\"block\"><semantics><mrow><munder><mrow><mi>lim</mi><mo>⁡</mo></mrow><mrow><mi mathvariant=\"normal\">Δ</mi><mi>x</mi><mo>→</mo><mn>0</mn></mrow></munder><mfrac><mrow><mi mathvariant=\"normal\">Δ</mi><mi>y</mi></mrow><mrow><mi mathvariant=\"normal\">Δ</mi><mi>x</mi></mrow></mfrac><mo>=</mo><munder><mrow><mi>lim</mi><mo>⁡</mo></mrow><mrow><mi mathvariant=\"normal\">Δ</mi><mi>x</mi><mo>→</mo><mn>1</mn></mrow></munder><mfrac><mrow><msup><mi>x</mi><mn>2</mn></msup><mo>−</mo><mn>1</mn></mrow><mrow><mi>x</mi><mo>−</mo><mn>1</mn></mrow></mfrac><mo>=</mo><munder><mrow><mi>lim</mi><mo>⁡</mo></mrow><mrow><mi mathvariant=\"normal\">Δ</mi><mi>x</mi><mo>→</mo><mn>1</mn></mrow></munder><mo stretchy=\"false\">(</mo><mi>x</mi><mo>+</mo><mn>1</mn><mo stretchy=\"false\">)</mo><mo>=</mo><mn>2</mn></mrow><annotation encoding=\"application/x-tex\">\\lim_{\\Delta x \\rightarrow 0} \\frac{\\Delta y}{\\Delta x} = \\lim_{\\Delta x \\rightarrow 1}\\frac{x^2 -1}{x - 1} = \\lim_{\\Delta x \\rightarrow 1}(x + 1) = 2</annotation></semantics></math></span><span class=\"katex-html\" aria-hidden=\"true\"><span class=\"base\"><span class=\"strut\" style=\"height:2.1047em;vertical-align:-0.7443em;\"></span><span class=\"mop op-limits\"><span class=\"vlist-t vlist-t2\"><span class=\"vlist-r\"><span class=\"vlist\" style=\"height:0.6944em;\"><span style=\"top:-2.3557em;margin-left:0em;\"><span class=\"pstrut\" style=\"height:3em;\"></span><span class=\"sizing reset-size6 size3 mtight\"><span class=\"mord mtight\"><span class=\"mord mtight\">Δ</span><span class=\"mord mathnormal mtight\">x</span><span class=\"mrel mtight\">→</span><span class=\"mord mtight\">0</span></span></span></span><span style=\"top:-3em;\"><span class=\"pstrut\" style=\"height:3em;\"></span><span><span class=\"mop\">lim</span></span></span></span><span class=\"vlist-s\">​</span></span><span class=\"vlist-r\"><span class=\"vlist\" style=\"height:0.7443em;\"><span></span></span></span></span></span><span class=\"mspace\" style=\"margin-right:0.1667em;\"></span><span class=\"mord\"><span class=\"mopen nulldelimiter\"></span><span class=\"mfrac\"><span class=\"vlist-t vlist-t2\"><span class=\"vlist-r\"><span class=\"vlist\" style=\"height:1.3603em;\"><span style=\"top:-2.314em;\"><span class=\"pstrut\" style=\"height:3em;\"></span><span class=\"mord\"><span class=\"mord\">Δ</span><span class=\"mord mathnormal\">x</span></span></span><span style=\"top:-3.23em;\"><span class=\"pstrut\" style=\"height:3em;\"></span><span class=\"frac-line\" style=\"border-bottom-width:0.04em;\"></span></span><span style=\"top:-3.677em;\"><span class=\"pstrut\" style=\"height:3em;\"></span><span class=\"mord\"><span class=\"mord\">Δ</span><span class=\"mord mathnormal\" style=\"margin-right:0.03588em;\">y</span></span></span></span><span class=\"vlist-s\">​</span></span><span class=\"vlist-r\"><span class=\"vlist\" style=\"height:0.686em;\"><span></span></span></span></span></span><span class=\"mclose nulldelimiter\"></span></span><span class=\"mspace\" style=\"margin-right:0.2778em;\"></span><span class=\"mrel\">=</span><span class=\"mspace\" style=\"margin-right:0.2778em;\"></span></span><span class=\"base\"><span class=\"strut\" style=\"height:2.2604em;vertical-align:-0.7693em;\"></span><span class=\"mop op-limits\"><span class=\"vlist-t vlist-t2\"><span class=\"vlist-r\"><span class=\"vlist\" style=\"height:0.6944em;\"><span style=\"top:-2.3557em;margin-left:0em;\"><span class=\"pstrut\" style=\"height:3em;\"></span><span class=\"sizing reset-size6 size3 mtight\"><span class=\"mord mtight\"><span class=\"mord mtight\">Δ</span><span class=\"mord mathnormal mtight\">x</span><span class=\"mrel mtight\">→</span><span class=\"mord mtight\">1</span></span></span></span><span style=\"top:-3em;\"><span class=\"pstrut\" style=\"height:3em;\"></span><span><span class=\"mop\">lim</span></span></span></span><span class=\"vlist-s\">​</span></span><span class=\"vlist-r\"><span class=\"vlist\" style=\"height:0.7443em;\"><span></span></span></span></span></span><span class=\"mspace\" style=\"margin-right:0.1667em;\"></span><span class=\"mord\"><span class=\"mopen nulldelimiter\"></span><span class=\"mfrac\"><span class=\"vlist-t vlist-t2\"><span class=\"vlist-r\"><span class=\"vlist\" style=\"height:1.4911em;\"><span style=\"top:-2.314em;\"><span class=\"pstrut\" style=\"height:3em;\"></span><span class=\"mord\"><span class=\"mord mathnormal\">x</span><span class=\"mspace\" style=\"margin-right:0.2222em;\"></span><span class=\"mbin\">−</span><span class=\"mspace\" style=\"margin-right:0.2222em;\"></span><span class=\"mord\">1</span></span></span><span style=\"top:-3.23em;\"><span class=\"pstrut\" style=\"height:3em;\"></span><span class=\"frac-line\" style=\"border-bottom-width:0.04em;\"></span></span><span style=\"top:-3.677em;\"><span class=\"pstrut\" style=\"height:3em;\"></span><span class=\"mord\"><span class=\"mord\"><span class=\"mord mathnormal\">x</span><span class=\"msupsub\"><span class=\"vlist-t\"><span class=\"vlist-r\"><span class=\"vlist\" style=\"height:0.8141em;\"><span style=\"top:-3.063em;margin-right:0.05em;\"><span class=\"pstrut\" style=\"height:2.7em;\"></span><span class=\"sizing reset-size6 size3 mtight\"><span class=\"mord mtight\">2</span></span></span></span></span></span></span></span><span class=\"mspace\" style=\"margin-right:0.2222em;\"></span><span class=\"mbin\">−</span><span class=\"mspace\" style=\"margin-right:0.2222em;\"></span><span class=\"mord\">1</span></span></span></span><span class=\"vlist-s\">​</span></span><span class=\"vlist-r\"><span class=\"vlist\" style=\"height:0.7693em;\"><span></span></span></span></span></span><span class=\"mclose nulldelimiter\"></span></span><span class=\"mspace\" style=\"margin-right:0.2778em;\"></span><span class=\"mrel\">=</span><span class=\"mspace\" style=\"margin-right:0.2778em;\"></span></span><span class=\"base\"><span class=\"strut\" style=\"height:1.4943em;vertical-align:-0.7443em;\"></span><span class=\"mop op-limits\"><span class=\"vlist-t vlist-t2\"><span class=\"vlist-r\"><span class=\"vlist\" style=\"height:0.6944em;\"><span style=\"top:-2.3557em;margin-left:0em;\"><span class=\"pstrut\" style=\"height:3em;\"></span><span class=\"sizing reset-size6 size3 mtight\"><span class=\"mord mtight\"><span class=\"mord mtight\">Δ</span><span class=\"mord mathnormal mtight\">x</span><span class=\"mrel mtight\">→</span><span class=\"mord mtight\">1</span></span></span></span><span style=\"top:-3em;\"><span class=\"pstrut\" style=\"height:3em;\"></span><span><span class=\"mop\">lim</span></span></span></span><span class=\"vlist-s\">​</span></span><span class=\"vlist-r\"><span class=\"vlist\" style=\"height:0.7443em;\"><span></span></span></span></span></span><span class=\"mopen\">(</span><span class=\"mord mathnormal\">x</span><span class=\"mspace\" style=\"margin-right:0.2222em;\"></span><span class=\"mbin\">+</span><span class=\"mspace\" style=\"margin-right:0.2222em;\"></span></span><span class=\"base\"><span class=\"strut\" style=\"height:1em;vertical-align:-0.25em;\"></span><span class=\"mord\">1</span><span class=\"mclose\">)</span><span class=\"mspace\" style=\"margin-right:0.2778em;\"></span><span class=\"mrel\">=</span><span class=\"mspace\" style=\"margin-right:0.2778em;\"></span></span><span class=\"base\"><span class=\"strut\" style=\"height:0.6444em;\"></span><span class=\"mord\">2</span></span></span></span></span></p>\n<p>故此抛物线在点P（1,1）处的切线斜率为2，因此方程为<br>\n<span class=\"katex\"><span class=\"katex-mathml\"><math xmlns=\"http://www.w3.org/1998/Math/MathML\"><semantics><mrow><mi>y</mi><mo>−</mo><mn>1</mn><mo>=</mo><mn>2</mn><mo stretchy=\"false\">(</mo><mi>x</mi><mo>−</mo><mn>1</mn><mo stretchy=\"false\">)</mo></mrow><annotation encoding=\"application/x-tex\">y - 1 = 2(x - 1)</annotation></semantics></math></span><span class=\"katex-html\" aria-hidden=\"true\"><span class=\"base\"><span class=\"strut\" style=\"height:0.7778em;vertical-align:-0.1944em;\"></span><span class=\"mord mathnormal\" style=\"margin-right:0.03588em;\">y</span><span class=\"mspace\" style=\"margin-right:0.2222em;\"></span><span class=\"mbin\">−</span><span class=\"mspace\" style=\"margin-right:0.2222em;\"></span></span><span class=\"base\"><span class=\"strut\" style=\"height:0.6444em;\"></span><span class=\"mord\">1</span><span class=\"mspace\" style=\"margin-right:0.2778em;\"></span><span class=\"mrel\">=</span><span class=\"mspace\" style=\"margin-right:0.2778em;\"></span></span><span class=\"base\"><span class=\"strut\" style=\"height:1em;vertical-align:-0.25em;\"></span><span class=\"mord\">2</span><span class=\"mopen\">(</span><span class=\"mord mathnormal\">x</span><span class=\"mspace\" style=\"margin-right:0.2222em;\"></span><span class=\"mbin\">−</span><span class=\"mspace\" style=\"margin-right:0.2222em;\"></span></span><span class=\"base\"><span class=\"strut\" style=\"height:1em;vertical-align:-0.25em;\"></span><span class=\"mord\">1</span><span class=\"mclose\">)</span></span></span></span>即<span class=\"katex\"><span class=\"katex-mathml\"><math xmlns=\"http://www.w3.org/1998/Math/MathML\"><semantics><mrow><mi>y</mi><mo>=</mo><mn>2</mn><mi>x</mi><mo>−</mo><mn>1</mn></mrow><annotation encoding=\"application/x-tex\">y = 2x - 1</annotation></semantics></math></span><span class=\"katex-html\" aria-hidden=\"true\"><span class=\"base\"><span class=\"strut\" style=\"height:0.625em;vertical-align:-0.1944em;\"></span><span class=\"mord mathnormal\" style=\"margin-right:0.03588em;\">y</span><span class=\"mspace\" style=\"margin-right:0.2778em;\"></span><span class=\"mrel\">=</span><span class=\"mspace\" style=\"margin-right:0.2778em;\"></span></span><span class=\"base\"><span class=\"strut\" style=\"height:0.7278em;vertical-align:-0.0833em;\"></span><span class=\"mord\">2</span><span class=\"mord mathnormal\">x</span><span class=\"mspace\" style=\"margin-right:0.2222em;\"></span><span class=\"mbin\">−</span><span class=\"mspace\" style=\"margin-right:0.2222em;\"></span></span><span class=\"base\"><span class=\"strut\" style=\"height:0.6444em;\"></span><span class=\"mord\">1</span></span></span></span></p>\n<p><img src=\"/assets/17362527181518028.png\" alt=\"抛物线切线\"></p>\n\n      </div>\n      <div class=\"md-sidebar-toc\">\n<div class=\"md-toc\">\n<details style=\"padding:0;;padding-left:0px;\" open=\"\">\n        <summary class=\"md-toc-link-wrapper\">\n          <a href=\"#导数-微分及其应用\" class=\"md-toc-link\"><p>导数、微分及其应用</p>\n</a>\n          </summary>\n        <div>\n          <details style=\"padding:0;;padding-left:24px;\" open=\"\">\n        <summary class=\"md-toc-link-wrapper\">\n          <a href=\"#导数与微分\" class=\"md-toc-link\"><p>导数与微分</p>\n</a>\n          </summary>\n        <div>\n          <div class=\"md-toc-link-wrapper\" style=\"padding:0;;display:list-item;list-style:square;margin-left:42px\">\n          <a href=\"#导数的概念\" class=\"md-toc-link\">\n            <p>导数的概念</p>\n\n          </a></div><div class=\"md-toc-link-wrapper\" style=\"padding:0;;display:list-item;list-style:square;margin-left:42px\">\n          <a href=\"#例-求函数yx2在点p11处的切线\" class=\"md-toc-link\">\n            <p>例 求函数<span class=\"katex\"><span class=\"katex-mathml\"><math xmlns=\"http://www.w3.org/1998/Math/MathML\"><semantics><mrow><mi>y</mi><mo>=</mo><msup><mi>x</mi><mn>2</mn></msup></mrow><annotation encoding=\"application/x-tex\">y=x^2</annotation></semantics></math></span><span class=\"katex-html\" aria-hidden=\"true\"><span class=\"base\"><span class=\"strut\" style=\"height:0.625em;vertical-align:-0.1944em;\"></span><span class=\"mord mathnormal\" style=\"margin-right:0.03588em;\">y</span><span class=\"mspace\" style=\"margin-right:0.2778em;\"></span><span class=\"mrel\">=</span><span class=\"mspace\" style=\"margin-right:0.2778em;\"></span></span><span class=\"base\"><span class=\"strut\" style=\"height:0.8141em;\"></span><span class=\"mord\"><span class=\"mord mathnormal\">x</span><span class=\"msupsub\"><span class=\"vlist-t\"><span class=\"vlist-r\"><span class=\"vlist\" style=\"height:0.8141em;\"><span style=\"top:-3.063em;margin-right:0.05em;\"><span class=\"pstrut\" style=\"height:2.7em;\"></span><span class=\"sizing reset-size6 size3 mtight\"><span class=\"mord mtight\">2</span></span></span></span></span></span></span></span></span></span></span>在点P(1,1)处的切线</p>\n\n          </a></div>\n        </div>\n      </details>\n    \n        </div>\n      </details>\n    \n</div>\n</div>\n      <a id=\"sidebar-toc-btn\">≡</a>\n    \n    \n    \n    \n    \n    \n<script>\n\nvar sidebarTOCBtn = document.getElementById('sidebar-toc-btn')\nsidebarTOCBtn.addEventListener('click', function(event) {\n  event.stopPropagation()\n  if (document.body.hasAttribute('html-show-sidebar-toc')) {\n    document.body.removeAttribute('html-show-sidebar-toc')\n  } else {\n    document.body.setAttribute('html-show-sidebar-toc', true)\n  }\n})\n</script>\n      \n  \n    "},"title":"02.导数、微分及其应用"},"__N_SSG":true}